webcash/__init__.py
webcash/exceptions.py
webcash/utils.py
webcash/wallet.py
webcash/walletclient.py
webcash/webcashbase.py
webcash-0.0.5.dist-info/LICENSE
webcash-0.0.5.dist-info/METADATA
webcash-0.0.5.dist-info/WHEEL
webcash-0.0.5.dist-info/entry_points.txt
webcash-0.0.5.dist-info/top_level.txt
webcash-0.0.5.dist-info/RECORD
