Metadata-Version: 2.1
Name: webcash
Version: 0.0.5
Summary: Webcash is an experimental "e-cash" (electronic cash)
Home-page: https://github.com/kanzure/webcash
Author: Bryan Bishop
Author-email: kanzure@gmail.com
Project-URL: Bug Tracker, https://github.com/kanzure/webcash/issues
Classifier: Programming Language :: Python :: 3
Classifier: License :: OSI Approved :: BSD License
Classifier: Operating System :: OS Independent
Requires-Python: >=3.6
License-File: LICENSE
Requires-Dist: requests
Requires-Dist: click
Requires-Dist: filelock
